pyschwab/__init__.py
pyschwab/auth.py
pyschwab/exceptions.py
pyschwab/log.py
pyschwab/market.py
pyschwab/market_models.py
pyschwab/trading.py
pyschwab/trading_models.py
pyschwab/types.py
pyschwab/user_input.py
pyschwab/utils.py
pyschwab-0.0.3.dist-info/LICENSE
pyschwab-0.0.3.dist-info/METADATA
pyschwab-0.0.3.dist-info/WHEEL
pyschwab-0.0.3.dist-info/RECORD
