Metadata-Version: 2.1
Name: pyschwab
Version: 0.0.3
Summary: A Python library for the Schwab trading API
Home-page: https://github.com/hzheng/pyschwab
License: MIT
Keywords: finance,trading,schwab,api,python
Author: Hui Zheng
Author-email: xyz.dll@gmail.com
Requires-Python: >=3.11,<4.0
Classifier: Development Status :: 3 - Alpha
Classifier: Intended Audience :: Developers
Classifier: License :: OSI Approved :: MIT License
Classifier: Programming Language :: Python :: 3
Classifier: Programming Language :: Python :: 3.11
Classifier: Programming Language :: Python :: 3.12
Classifier: Topic :: Office/Business :: Financial
Classifier: Topic :: Software Development :: Libraries
Requires-Dist: holidays (>=0.48,<0.49)
Requires-Dist: pydantic (>=2.7.1,<3.0.0)
Requires-Dist: python-dotenv (>=1.0.1,<2.0.0)
Requires-Dist: pyyaml (>=6.0.1,<7.0.0)
Requires-Dist: requests (>=2.31.0,<3.0.0)
Project-URL: Documentation, https://pyschwab.readthedocs.io
Project-URL: Repository, https://github.com/hzheng/pyschwab
